src/__init__.py
src/main.py
src/core/__init__.py
src/core/commands.py
src/core/encryption.py
src/core/utils.py
src/levels/__init__.py
src/levels/level1.py
src/levels/level2.py
src/levels/level3.py
utils/__init__.py
utils/ui.py
HackQuest-1.1.1.dist-info/LICENSE
HackQuest-1.1.1.dist-info/METADATA
HackQuest-1.1.1.dist-info/WHEEL
HackQuest-1.1.1.dist-info/entry_points.txt
HackQuest-1.1.1.dist-info/top_level.txt
HackQuest-1.1.1.dist-info/RECORD
