Metadata-Version: 2.2
Name: HackQuest
Version: 1.1.1
Summary: A terminal-based hacking simulator game
Home-page: https://github.com/SMTNDev/HackQuest
Author: SMTNDev
Author-email: smtndeveloper@gmail.com
Classifier: Programming Language :: Python :: 3.8
Classifier: License :: OSI Approved :: MIT License
Classifier: Operating System :: OS Independent
Requires-Python: >=3.8
License-File: LICENSE
Requires-Dist: colorama==0.4.6
Requires-Dist: termcolor==2.3.0
Requires-Dist: pyfiglet==0.8.post1
Requires-Dist: rich==13.5.2
Requires-Dist: blessings==1.7
Requires-Dist: cryptography==39.0.0
Requires-Dist: curses-2048
Dynamic: author
Dynamic: author-email
Dynamic: classifier
Dynamic: description
Dynamic: description-content-type
Dynamic: home-page
Dynamic: requires-dist
Dynamic: requires-python
Dynamic: summary
